mycalc/calculator.py
seongjin0702-0.0.1.dist-info/METADATA
seongjin0702-0.0.1.dist-info/WHEEL
seongjin0702-0.0.1.dist-info/top_level.txt
seongjin0702-0.0.1.dist-info/RECORD
