Metadata-Version: 2.1
Name: seongjin0702
Version: 0.0.1
Summary: my calculator
Home-page: https://github.com/KimSeongjin72/calc0001
Download-URL: https://github.com/KimSeongjin72/calc0001/archive/refs/tags/v0.0.1.zip
Author: seong jin
License: UNKNOWN
Platform: UNKNOWN
Classifier: Programming Language :: Python :: 3
